setup.py
mongoq/__init__.py
mongoq.egg-info/PKG-INFO
mongoq.egg-info/SOURCES.txt
mongoq.egg-info/dependency_links.txt
mongoq.egg-info/top_level.txt