Metadata-Version: 1.0
Name: mongoq
Version: 0.1
Summary: mongoq generates MongoDB queries from simple python expressions
Home-page: https://github.com/alonho/mongoq
Author: Alon Horev
Author-email: alonho@gmail.com
License: BSD
Platform: UNKNOWN
Classifier: Development Status :: 3 - Alpha
Classifier: Intended Audience :: Developers
Classifier: License :: OSI Approved :: BSD License
Classifier: Programming Language :: Python :: 2
Classifier: Programming Language :: Python :: 3
